{
  "_fv": 57,
  "_type": "recipe",
  "definition": {
    "recipeType": "Crafting",
    "recipeRetstackSize": 4,
    "group": "",
    "cookingBookCategory": "MISC",
    "xpReward": 0.0,
    "cookingTime": 200,
    "craftingBookCategory": "MISC",
    "recipeShapeless": false,
    "recipeSlots": [
      {
        "value": "CUSTOM:NyctocapPlanks"
      },
      {
        "value": ""
      },
      {
        "value": ""
      },
      {
        "value": "CUSTOM:NyctocapPlanks"
      },
      {
        "value": "CUSTOM:NyctocapPlanks"
      },
      {
        "value": ""
      },
      {
        "value": "CUSTOM:NyctocapPlanks"
      },
      {
        "value": "CUSTOM:NyctocapPlanks"
      },
      {
        "value": "CUSTOM:NyctocapPlanks"
      }
    ],
    "recipeReturnStack": {
      "value": "CUSTOM:NyctocapStairs"
    },
    "name": "nyctocap_stairs_craft",
    "namespace": "mod"
  }
}